processmcrat/.DS_Store
processmcrat/__init__.py
processmcrat/hydrosim_lib.py
processmcrat/hydrosim_plotting.py
processmcrat/mclib.py
processmcrat/mcrat_movie.py
processmcrat/mockobservations.py
processmcrat/plotting.py
processmcrat/process_hydrosim.py
processmcrat/processmcrat.py
processmcrat/read_process_files.py
processmcrat/.idea/misc.xml
processmcrat/.idea/modules.xml
processmcrat/.idea/processmcrat.iml
processmcrat/.idea/vcs.xml
processmcrat/.idea/workspace (tyler.parsotan@nasa.gov).xml
processmcrat/.idea/workspace.xml
processmcrat/.idea/inspectionProfiles/profiles_settings.xml
processmcrat/Data_files/Dataset_lundman_1.csv
processmcrat/Data_files/Dataset_lundman_2.csv
processmcrat/Data_files/FERMI_BEST_GRB.dat
processmcrat/Data_files/GRB_list.dat
processmcrat/Data_files/lundman_p_4_thetaj_0.1.csv
processmcrat/test/__init__.py
processmcrat-2.0.3.data/data/Data_files/Dataset_lundman_1.csv
processmcrat-2.0.3.data/data/Data_files/Dataset_lundman_2.csv
processmcrat-2.0.3.data/data/Data_files/FERMI_BEST_GRB.dat
processmcrat-2.0.3.data/data/Data_files/GRB_list.dat
processmcrat-2.0.3.data/data/Data_files/lundman_p_4_thetaj_0.1.csv
processmcrat-2.0.3.dist-info/LICENSE
processmcrat-2.0.3.dist-info/METADATA
processmcrat-2.0.3.dist-info/WHEEL
processmcrat-2.0.3.dist-info/top_level.txt
processmcrat-2.0.3.dist-info/RECORD
