Metadata-Version: 2.1
Name: processmcrat
Version: 2.0.3
Summary: The ProcessMCRaT library is a python package that can be used to process the output of the MCRaT code.
Home-page: https://github.com/parsotat/ProcessMCRaT
Author: Tyler Parsotan
Author-email: tyler.parsotan@nasa.gov
License: MIT
Keywords: astronomy radiation-transfer hydrodynamics
Classifier: Development Status :: 5 - Production/Stable
Classifier: Intended Audience :: Science/Research
Classifier: License :: OSI Approved :: MIT License
Classifier: Programming Language :: Python
Classifier: Programming Language :: Python :: 3
Classifier: Topic :: Scientific/Engineering :: Astronomy
Requires-Python: >=3.9
License-File: LICENSE
Requires-Dist: astropy (>=4.2.1)
Requires-Dist: cached-property (>=1.5.2)
Requires-Dist: certifi (>=2020.12.5)
Requires-Dist: cycler (>=0.10.0)
Requires-Dist: h5py (>=3.2.1)
Requires-Dist: kiwisolver (>=1.3.1)
Requires-Dist: matplotlib (>=3.4.1)
Requires-Dist: numexpr (>=2.7.3)
Requires-Dist: numpy (>=1.20.2)
Requires-Dist: Pillow (>=8.2.0)
Requires-Dist: pyerfa (>=1.7.3)
Requires-Dist: pyparsing (>=2.4.7)
Requires-Dist: python-dateutil (>=2.8.1)
Requires-Dist: scipy (>=1.6.2)
Requires-Dist: six (>=1.15.0)
Requires-Dist: tables (>=3.6.1)
Requires-Dist: gdown (>=4.3.0)
Requires-Dist: joblib (>=1.2.0)
